rajan_nse/CandleStickPatterns.py
rajan_nse/NseData.py
rajan_nse/Session.py
rajan_nse/Strategies.py
rajan_nse/TechnicalIndicators.py
rajan_nse/Visualization.py
rajan_nse/__init__.py
rajan_nse/helpers.py
rajan_nse/promoter.py
rajan_nse-1.3.0.dist-info/METADATA
rajan_nse-1.3.0.dist-info/WHEEL
rajan_nse-1.3.0.dist-info/licenses/LICENSE
rajan_nse-1.3.0.dist-info/RECORD
